masscode/__init__.py
masscode/cli.py
masscode/core/api.py
masscode/core/discovery.py
masscode/core/file.py
masscode/core/i.py
masscode/model/db.py
masscode/model/preferences.py
masscode/model/query.py
masscode/utils/__init__.py
masscode/utils/proc.py
masscode/utils/prop.py
masscode_py-1.0.0.dist-info/METADATA
masscode_py-1.0.0.dist-info/WHEEL
masscode_py-1.0.0.dist-info/entry_points.txt
masscode_py-1.0.0.dist-info/licenses/LICENSE
masscode_py-1.0.0.dist-info/RECORD
