Metadata-Version: 2.4
Name: masscode-py
Version: 1.0.0
Summary: python wrapper for masscode
Author-email: ZackaryW <36378555+ZackaryW@users.noreply.github.com>
License-File: LICENSE
Requires-Python: >=3.8
Requires-Dist: requests>=2.32.3
Provides-Extra: cli
Requires-Dist: click>=8.2.1; extra == 'cli'
Provides-Extra: fast
Requires-Dist: orjson>=3.10.18; extra == 'fast'
